[
  {
    "hash": "1267955590",
    "idx": 0,
    "concept": "75adf1c32d1e1da1da4d303a02d34aab",
    "x": 1075,
    "y": 328
  },
  {
    "hash": "2036914617",
    "idx": 1,
    "concept": "4511e9043a573455216aba5e4323792d",
    "x": 1272,
    "y": 1294
  },
  {
    "hash": "368588265",
    "idx": 2,
    "concept": "4e6e44fa305b8446cbea0b1342f3d0ae",
    "x": 127,
    "y": 487
  },
  {
    "hash": "780222961",
    "idx": 3,
    "concept": "72a8a020885e156dbb74e44db4bfcb1a",
    "x": 131,
    "y": 724
  },
  {
    "hash": "689628938",
    "idx": 4,
    "concept": "cd1c269a0300496b74d3451891b36def",
    "x": 136,
    "y": 920
  },
  {
    "hash": "727420038",
    "idx": 5,
    "concept": "f1773fd7751047467046dc0828b5a592",
    "x": 439,
    "y": 1091
  },
  {
    "hash": "1233329439",
    "idx": 6,
    "concept": "4e11c97b7eec9fa648619c9aa5d5a8a9",
    "x": 445,
    "y": 862
  },
  {
    "hash": "858405351",
    "idx": 7,
    "concept": "ffb4e225181c611ba60f6c015565d1f8",
    "x": 867,
    "y": 1118
  },
  {
    "hash": "1288045433",
    "idx": 8,
    "concept": "d055e058a7b761e05a25716584b08e92",
    "x": 1079,
    "y": 492
  },
  {
    "hash": "1111486480",
    "idx": 9,
    "concept": "879f3e7604f9ee0b239c4ce61e7d0ed5",
    "x": 1567,
    "y": 564
  },
  {
    "hash": "974659441",
    "idx": 10,
    "concept": "b8b8d8165b9ecc0e822dc76ef0570763",
    "x": 1943,
    "y": 650
  },
  {
    "hash": "564936324",
    "idx": 11,
    "concept": "e4d6d8ed447ec91d2311f33d3366a843",
    "x": 1951,
    "y": 926
  },
  {
    "hash": "388441366",
    "idx": 12,
    "concept": "493f18d964f7bad1cb0e80296939cc41",
    "x": 1953,
    "y": 1182
  },
  {
    "hash": "166955481",
    "idx": 13,
    "concept": "98765f3bcd71ea529cb9d003b9763543",
    "x": 1564,
    "y": 400
  },
  {
    "hash": "1736368298",
    "idx": 14,
    "concept": "228c6b3bedce48f135dfe3594e910b9f",
    "x": 1940,
    "y": 475
  },
  {
    "hash": "1222862213",
    "idx": 15,
    "concept": "eb763c12ffb1c5746992cb9c9839c04f",
    "x": 1341,
    "y": 883
  }
]