{
   "concepts" : [
      {
         "extent" : [
            "CEM",
            "CM",
            "GR",
            "PM",
            "RK"
         ],
         "intent" : [
            "K",
            "Time",
            "{X}"
         ]
      },
      {
         "extent" : [],
         "intent" : [
            "1/r",
            "<1,3>",
            "Affine Connection",
            "Asymptotic Form",
            "Balance of Momentum",
            "Bodies",
            "Body Force Density",
            "Body Stress",
            "c",
            "Charge Density",
            "Charged Bodies",
            "Charged M Bodies",
            "CM 2.2",
            "Coordinate Transformations",
            "Cotime",
            "E3",
            "E3R",
            "Einstein’s Eq",
            "Electric Fields",
            "EM Fields",
            "EM Signals",
            "Energy-momentum Tensor",
            "External Force",
            "F = ma",
            "Force Density",
            "GR 5.2",
            "GR 6.3",
            "Gravitational Fields",
            "Inertial Frame",
            "Interparticle Force",
            "K",
            "kappa",
            "Locality",
            "M Bodies",
            "M3",
            "M4",
            "Magnetic Fields",
            "Map",
            "Mass",
            "Mass Additivity",
            "Mass Conservation",
            "Mass Density",
            "Maxwell’s Eq",
            "Metric Tensor",
            "Moment of Momentum",
            "Non Gravitational Fields",
            "Particles",
            "Physical Systems",
            "PM 2.4",
            "PM 2.5",
            "PM 3.2",
            "Postulate",
            "Tensor Degeneration",
            "Time",
            "Time Range",
            "Velocity and Acceleration",
            "{XGR}",
            "{XR}",
            "{X}"
         ]
      },
      {
         "extent" : [
            "CEM",
            "GR",
            "RK"
         ],
         "intent" : [
            "1/r",
            "c",
            "Charged Bodies",
            "Charged M Bodies",
            "Electric Fields",
            "EM Fields",
            "EM Signals",
            "Force Density",
            "K",
            "M Bodies",
            "M3",
            "Magnetic Fields",
            "Maxwell’s Eq",
            "Physical Systems",
            "Time",
            "{X}"
         ]
      },
      {
         "extent" : [
            "GR",
            "RK"
         ],
         "intent" : [
            "1/r",
            "Bodies",
            "c",
            "Charged Bodies",
            "Charged M Bodies",
            "Cotime",
            "E3",
            "E3R",
            "Electric Fields",
            "EM Fields",
            "EM Signals",
            "Force Density",
            "Inertial Frame",
            "K",
            "M Bodies",
            "M3",
            "Magnetic Fields",
            "Maxwell’s Eq",
            "Particles",
            "Physical Systems",
            "Postulate",
            "Time",
            "Time Range",
            "{XR}",
            "{X}"
         ]
      },
      {
         "extent" : [
            "GR"
         ],
         "intent" : [
            "1/r",
            "<1,3>",
            "Affine Connection",
            "Asymptotic Form",
            "Bodies",
            "c",
            "Charged Bodies",
            "Charged M Bodies",
            "Coordinate Transformations",
            "Cotime",
            "E3",
            "E3R",
            "Einstein’s Eq",
            "Electric Fields",
            "EM Fields",
            "EM Signals",
            "Energy-momentum Tensor",
            "Force Density",
            "GR 5.2",
            "GR 6.3",
            "Gravitational Fields",
            "Inertial Frame",
            "K",
            "kappa",
            "Locality",
            "M Bodies",
            "M3",
            "M4",
            "Magnetic Fields",
            "Maxwell’s Eq",
            "Metric Tensor",
            "Non Gravitational Fields",
            "Particles",
            "Physical Systems",
            "Postulate",
            "Time",
            "Time Range",
            "{XGR}",
            "{XR}",
            "{X}"
         ]
      },
      {
         "extent" : [
            "CEM"
         ],
         "intent" : [
            "1/r",
            "Body Force Density",
            "c",
            "Charged Bodies",
            "Charged M Bodies",
            "Electric Fields",
            "EM Fields",
            "EM Signals",
            "Force Density",
            "K",
            "M Bodies",
            "M3",
            "Magnetic Fields",
            "Maxwell’s Eq",
            "Physical Systems",
            "Time",
            "{X}"
         ]
      },
      {
         "extent" : [
            "CM",
            "GR",
            "PM",
            "RK"
         ],
         "intent" : [
            "E3",
            "K",
            "Time",
            "{X}"
         ]
      },
      {
         "extent" : [
            "GR",
            "PM",
            "RK"
         ],
         "intent" : [
            "E3",
            "K",
            "Particles",
            "Postulate",
            "Time",
            "{X}"
         ]
      },
      {
         "extent" : [
            "PM"
         ],
         "intent" : [
            "E3",
            "External Force",
            "F = ma",
            "Interparticle Force",
            "K",
            "Mass",
            "Particles",
            "PM 2.4",
            "PM 2.5",
            "PM 3.2",
            "Postulate",
            "Time",
            "{X}"
         ]
      },
      {
         "extent" : [
            "CM",
            "GR",
            "RK"
         ],
         "intent" : [
            "Bodies",
            "E3",
            "K",
            "Time",
            "{X}"
         ]
      },
      {
         "extent" : [
            "CM"
         ],
         "intent" : [
            "Balance of Momentum",
            "Bodies",
            "Body Force Density",
            "Body Stress",
            "Charge Density",
            "CM 2.2",
            "E3",
            "K",
            "Map",
            "Mass Additivity",
            "Mass Conservation",
            "Mass Density",
            "Moment of Momentum",
            "Time",
            "Velocity and Acceleration",
            "{X}"
         ]
      },
      {
         "extent" : [
            "CEM",
            "CM"
         ],
         "intent" : [
            "Body Force Density",
            "K",
            "Time",
            "{X}"
         ]
      }
   ],
   "context" : {
      "CEM" : {
         "attributes" : [
            "1/r",
            "Body Force Density",
            "c",
            "Charged Bodies",
            "Charged M Bodies",
            "Electric Fields",
            "EM Fields",
            "EM Signals",
            "Force Density",
            "K",
            "M Bodies",
            "M3",
            "Magnetic Fields",
            "Maxwell’s Eq",
            "Physical Systems",
            "Time",
            "{X}"
         ],
         "id" : "CEM",
         "name" : "Classical Electromagnetism"
      },
      "CM" : {
         "attributes" : [
            "Balance of Momentum",
            "Bodies",
            "Body Force Density",
            "Body Stress",
            "Charge Density",
            "CM 2.2",
            "E3",
            "K",
            "Map",
            "Mass Additivity",
            "Mass Conservation",
            "Mass Density",
            "Moment of Momentum",
            "Time",
            "Velocity and Acceleration",
            "{X}"
         ],
         "id" : "CM",
         "name" : "Continuum Mechanics"
      },
      "GR" : {
         "attributes" : [
            "1/r",
            "<1,3>",
            "Affine Connection",
            "Asymptotic Form",
            "Bodies",
            "c",
            "Charged Bodies",
            "Charged M Bodies",
            "Coordinate Transformations",
            "Cotime",
            "E3",
            "E3R",
            "Einstein’s Eq",
            "Electric Fields",
            "EM Fields",
            "EM Signals",
            "Energy-momentum Tensor",
            "Force Density",
            "GR 5.2",
            "GR 6.3",
            "Gravitational Fields",
            "Inertial Frame",
            "K",
            "kappa",
            "Locality",
            "M Bodies",
            "M3",
            "M4",
            "Magnetic Fields",
            "Maxwell’s Eq",
            "Metric Tensor",
            "Non Gravitational Fields",
            "Particles",
            "Physical Systems",
            "Postulate",
            "Time",
            "Time Range",
            "{XGR}",
            "{XR}",
            "{X}"
         ],
         "id" : "GR",
         "name" : "General Relativity"
      },
      "PM" : {
         "attributes" : [
            "E3",
            "External Force",
            "F = ma",
            "Interparticle Force",
            "K",
            "Mass",
            "Particles",
            "PM 2.4",
            "PM 2.5",
            "PM 3.2",
            "Postulate",
            "Time",
            "{X}"
         ],
         "id" : "PM",
         "name" : "Particle Mechanics"
      },
      "RK" : {
         "attributes" : [
            "1/r",
            "Bodies",
            "c",
            "Charged Bodies",
            "Charged M Bodies",
            "Cotime",
            "E3",
            "E3R",
            "Electric Fields",
            "EM Fields",
            "EM Signals",
            "Force Density",
            "Inertial Frame",
            "K",
            "M Bodies",
            "M3",
            "Magnetic Fields",
            "Maxwell’s Eq",
            "Particles",
            "Physical Systems",
            "Postulate",
            "Time",
            "Time Range",
            "{XR}",
            "{X}"
         ],
         "id" : "RK",
         "name" : "Relativistic Kinematics"
      }
   },
   "links" : [
      {
         "source" : 0,
         "target" : 2
      },
      {
         "source" : 0,
         "target" : 6
      },
      {
         "source" : 0,
         "target" : 11
      },
      {
         "source" : 2,
         "target" : 3
      },
      {
         "source" : 2,
         "target" : 5
      },
      {
         "source" : 3,
         "target" : 4
      },
      {
         "source" : 4,
         "target" : 1
      },
      {
         "source" : 5,
         "target" : 1
      },
      {
         "source" : 6,
         "target" : 7
      },
      {
         "source" : 6,
         "target" : 9
      },
      {
         "source" : 7,
         "target" : 3
      },
      {
         "source" : 7,
         "target" : 8
      },
      {
         "source" : 8,
         "target" : 1
      },
      {
         "source" : 9,
         "target" : 3
      },
      {
         "source" : 9,
         "target" : 10
      },
      {
         "source" : 10,
         "target" : 1
      },
      {
         "source" : 11,
         "target" : 10
      },
      {
         "source" : 11,
         "target" : 5
      }
   ],
   "nodes" : [
      {
         "children" : [
            "1161595138",
            "1142980638",
            "1142947907"
         ],
         "concept" : {
            "extent" : [
               "CEM",
               "CM",
               "GR",
               "PM",
               "RK"
            ],
            "intent" : [
               "K",
               "Time",
               "{X}"
            ]
         },
         "hash" : "1142947871",
         "idx" : 0,
         "labelAttributes" : [
            "{X}",
            "Time",
            "K"
         ],
         "labelObjects" : [],
         "level" : "5",
         "parents" : []
      },
      {
         "children" : [],
         "concept" : {
            "extent" : [],
            "intent" : [
               "1/r",
               "<1,3>",
               "Affine Connection",
               "Asymptotic Form",
               "Balance of Momentum",
               "Bodies",
               "Body Force Density",
               "Body Stress",
               "c",
               "Charge Density",
               "Charged Bodies",
               "Charged M Bodies",
               "CM 2.2",
               "Coordinate Transformations",
               "Cotime",
               "E3",
               "E3R",
               "Einstein’s Eq",
               "Electric Fields",
               "EM Fields",
               "EM Signals",
               "Energy-momentum Tensor",
               "External Force",
               "F = ma",
               "Force Density",
               "GR 5.2",
               "GR 6.3",
               "Gravitational Fields",
               "Inertial Frame",
               "Interparticle Force",
               "K",
               "kappa",
               "Locality",
               "M Bodies",
               "M3",
               "M4",
               "Magnetic Fields",
               "Map",
               "Mass",
               "Mass Additivity",
               "Mass Conservation",
               "Mass Density",
               "Maxwell’s Eq",
               "Metric Tensor",
               "Moment of Momentum",
               "Non Gravitational Fields",
               "Particles",
               "Physical Systems",
               "PM 2.4",
               "PM 2.5",
               "PM 3.2",
               "Postulate",
               "Tensor Degeneration",
               "Time",
               "Time Range",
               "Velocity and Acceleration",
               "{XGR}",
               "{XR}",
               "{X}"
            ]
         },
         "hash" : "-134217728",
         "idx" : 1,
         "labelAttributes" : [
            "Tensor Degeneration"
         ],
         "labelObjects" : [],
         "level" : "0",
         "parents" : [
            "-665386700",
            "1161595222",
            "1693433928",
            "1151369554"
         ]
      },
      {
         "children" : [
            "1467287843",
            "1161595222"
         ],
         "concept" : {
            "extent" : [
               "CEM",
               "GR",
               "RK"
            ],
            "intent" : [
               "1/r",
               "c",
               "Charged Bodies",
               "Charged M Bodies",
               "Electric Fields",
               "EM Fields",
               "EM Signals",
               "Force Density",
               "K",
               "M Bodies",
               "M3",
               "Magnetic Fields",
               "Maxwell’s Eq",
               "Physical Systems",
               "Time",
               "{X}"
            ]
         },
         "hash" : "1161595138",
         "idx" : 2,
         "labelAttributes" : [
            "Physical Systems",
            "Maxwell’s Eq",
            "Magnetic Fields",
            "M3",
            "M Bodies",
            "Force Density",
            "EM Signals",
            "EM Fields",
            "Electric Fields",
            "Charged M Bodies",
            "Charged Bodies",
            "c",
            "1/r"
         ],
         "labelObjects" : [],
         "level" : "3",
         "parents" : [
            "1142947871"
         ]
      },
      {
         "children" : [
            "-665386700"
         ],
         "concept" : {
            "extent" : [
               "GR",
               "RK"
            ],
            "intent" : [
               "1/r",
               "Bodies",
               "c",
               "Charged Bodies",
               "Charged M Bodies",
               "Cotime",
               "E3",
               "E3R",
               "Electric Fields",
               "EM Fields",
               "EM Signals",
               "Force Density",
               "Inertial Frame",
               "K",
               "M Bodies",
               "M3",
               "Magnetic Fields",
               "Maxwell’s Eq",
               "Particles",
               "Physical Systems",
               "Postulate",
               "Time",
               "Time Range",
               "{XR}",
               "{X}"
            ]
         },
         "hash" : "1467287843",
         "idx" : 3,
         "labelAttributes" : [
            "{XR}",
            "Time Range",
            "Inertial Frame",
            "E3R",
            "Cotime"
         ],
         "labelObjects" : [
            "RK"
         ],
         "level" : "2",
         "parents" : [
            "1161595138",
            "1143521308",
            "1142980662"
         ]
      },
      {
         "children" : [
            "-134217728"
         ],
         "concept" : {
            "extent" : [
               "GR"
            ],
            "intent" : [
               "1/r",
               "<1,3>",
               "Affine Connection",
               "Asymptotic Form",
               "Bodies",
               "c",
               "Charged Bodies",
               "Charged M Bodies",
               "Coordinate Transformations",
               "Cotime",
               "E3",
               "E3R",
               "Einstein’s Eq",
               "Electric Fields",
               "EM Fields",
               "EM Signals",
               "Energy-momentum Tensor",
               "Force Density",
               "GR 5.2",
               "GR 6.3",
               "Gravitational Fields",
               "Inertial Frame",
               "K",
               "kappa",
               "Locality",
               "M Bodies",
               "M3",
               "M4",
               "Magnetic Fields",
               "Maxwell’s Eq",
               "Metric Tensor",
               "Non Gravitational Fields",
               "Particles",
               "Physical Systems",
               "Postulate",
               "Time",
               "Time Range",
               "{XGR}",
               "{XR}",
               "{X}"
            ]
         },
         "hash" : "-665386700",
         "idx" : 4,
         "labelAttributes" : [
            "{XGR}",
            "Non Gravitational Fields",
            "Metric Tensor",
            "M4",
            "Locality",
            "kappa",
            "Gravitational Fields",
            "GR 6.3",
            "GR 5.2",
            "Energy-momentum Tensor",
            "Einstein’s Eq",
            "Coordinate Transformations",
            "Asymptotic Form",
            "Affine Connection",
            "<1,3>"
         ],
         "labelObjects" : [
            "GR"
         ],
         "level" : "1",
         "parents" : [
            "1467287843"
         ]
      },
      {
         "children" : [
            "-134217728"
         ],
         "concept" : {
            "extent" : [
               "CEM"
            ],
            "intent" : [
               "1/r",
               "Body Force Density",
               "c",
               "Charged Bodies",
               "Charged M Bodies",
               "Electric Fields",
               "EM Fields",
               "EM Signals",
               "Force Density",
               "K",
               "M Bodies",
               "M3",
               "Magnetic Fields",
               "Maxwell’s Eq",
               "Physical Systems",
               "Time",
               "{X}"
            ]
         },
         "hash" : "1161595222",
         "idx" : 5,
         "labelAttributes" : [],
         "labelObjects" : [
            "CEM"
         ],
         "level" : "1",
         "parents" : [
            "1161595138",
            "1142947907"
         ]
      },
      {
         "children" : [
            "1143521308",
            "1142980662"
         ],
         "concept" : {
            "extent" : [
               "CM",
               "GR",
               "PM",
               "RK"
            ],
            "intent" : [
               "E3",
               "K",
               "Time",
               "{X}"
            ]
         },
         "hash" : "1142980638",
         "idx" : 6,
         "labelAttributes" : [
            "E3"
         ],
         "labelObjects" : [],
         "level" : "4",
         "parents" : [
            "1142947871"
         ]
      },
      {
         "children" : [
            "1467287843",
            "1693433928"
         ],
         "concept" : {
            "extent" : [
               "GR",
               "PM",
               "RK"
            ],
            "intent" : [
               "E3",
               "K",
               "Particles",
               "Postulate",
               "Time",
               "{X}"
            ]
         },
         "hash" : "1143521308",
         "idx" : 7,
         "labelAttributes" : [
            "Postulate",
            "Particles"
         ],
         "labelObjects" : [],
         "level" : "3",
         "parents" : [
            "1142980638"
         ]
      },
      {
         "children" : [
            "-134217728"
         ],
         "concept" : {
            "extent" : [
               "PM"
            ],
            "intent" : [
               "E3",
               "External Force",
               "F = ma",
               "Interparticle Force",
               "K",
               "Mass",
               "Particles",
               "PM 2.4",
               "PM 2.5",
               "PM 3.2",
               "Postulate",
               "Time",
               "{X}"
            ]
         },
         "hash" : "1693433928",
         "idx" : 8,
         "labelAttributes" : [
            "PM 3.2",
            "PM 2.5",
            "PM 2.4",
            "Mass",
            "Interparticle Force",
            "F = ma",
            "External Force"
         ],
         "labelObjects" : [
            "PM"
         ],
         "level" : "1",
         "parents" : [
            "1143521308"
         ]
      },
      {
         "children" : [
            "1467287843",
            "1151369554"
         ],
         "concept" : {
            "extent" : [
               "CM",
               "GR",
               "RK"
            ],
            "intent" : [
               "Bodies",
               "E3",
               "K",
               "Time",
               "{X}"
            ]
         },
         "hash" : "1142980662",
         "idx" : 9,
         "labelAttributes" : [
            "Bodies"
         ],
         "labelObjects" : [],
         "level" : "3",
         "parents" : [
            "1142980638"
         ]
      },
      {
         "children" : [
            "-134217728"
         ],
         "concept" : {
            "extent" : [
               "CM"
            ],
            "intent" : [
               "Balance of Momentum",
               "Bodies",
               "Body Force Density",
               "Body Stress",
               "Charge Density",
               "CM 2.2",
               "E3",
               "K",
               "Map",
               "Mass Additivity",
               "Mass Conservation",
               "Mass Density",
               "Moment of Momentum",
               "Time",
               "Velocity and Acceleration",
               "{X}"
            ]
         },
         "hash" : "1151369554",
         "idx" : 10,
         "labelAttributes" : [
            "Velocity and Acceleration",
            "Moment of Momentum",
            "Mass Density",
            "Mass Conservation",
            "Mass Additivity",
            "Map",
            "CM 2.2",
            "Charge Density",
            "Body Stress",
            "Balance of Momentum"
         ],
         "labelObjects" : [
            "CM"
         ],
         "level" : "1",
         "parents" : [
            "1142980662",
            "1142947907"
         ]
      },
      {
         "children" : [
            "1151369554",
            "1161595222"
         ],
         "concept" : {
            "extent" : [
               "CEM",
               "CM"
            ],
            "intent" : [
               "Body Force Density",
               "K",
               "Time",
               "{X}"
            ]
         },
         "hash" : "1142947907",
         "idx" : 11,
         "labelAttributes" : [
            "Body Force Density"
         ],
         "labelObjects" : [],
         "level" : "2",
         "parents" : [
            "1142947871"
         ]
      }
   ]
}
